cubeofrubik/Color.py
cubeofrubik/RubiksCube.py
cubeofrubik/RubiksCubeAlgorithms.py
cubeofrubik/RubiksCubeInterface.py
cubeofrubik/__init__.py
cubeofrubik/main.py
cubeofrubik-1.0.0.dist-info/LICENSE
cubeofrubik-1.0.0.dist-info/METADATA
cubeofrubik-1.0.0.dist-info/WHEEL
cubeofrubik-1.0.0.dist-info/top_level.txt
cubeofrubik-1.0.0.dist-info/RECORD
