Metadata-Version: 2.1
Name: cubeofrubik
Version: 1.0.0
Summary: A Rubik's cube model and solver
Author-email: Breno Levi <blevic@proton.me>
License: MIT License        
Project-URL: Homepage, https://github.com/blevic/cubeofrubik
Project-URL: Bug Tracker, https://github.com/blevic/cubeofrubik/issues
Keywords: rubik's cube,layer-by-layer,singmaster,puzzle,solver,cube of rubik,kociemba
Classifier: Programming Language :: Python :: 3
Classifier: License :: OSI Approved :: MIT License
Classifier: Operating System :: OS Independent
Requires-Python: >=3.6
License-File: LICENSE
Requires-Dist: kociemba (>=1.2.1)
